qt_dataviewer/__init__.py
qt_dataviewer/data_file_browser.py
qt_dataviewer/dataset_viewer.py
qt_dataviewer/abstract/__init__.py
qt_dataviewer/abstract/dataset.py
qt_dataviewer/abstract/dataset_description.py
qt_dataviewer/abstract/dataset_list.py
qt_dataviewer/abstract/dataset_store.py
qt_dataviewer/abstract/types.py
qt_dataviewer/browser_ui/__init__.py
qt_dataviewer/browser_ui/browser_dataset_list.py
qt_dataviewer/browser_ui/dataset_list_view.py
qt_dataviewer/browser_ui/datelist.py
qt_dataviewer/browser_ui/filters.py
qt_dataviewer/browser_ui/main_window.py
qt_dataviewer/browser_ui/top_bar.py
qt_dataviewer/core_tools/__init__.py
qt_dataviewer/core_tools/data_browser.py
qt_dataviewer/core_tools/dataset.py
qt_dataviewer/core_tools/dataset_store.py
qt_dataviewer/core_tools/dataset_viewer.py
qt_dataviewer/dataset_files/__init__.py
qt_dataviewer/dataset_files/core_tools_files.py
qt_dataviewer/dataset_files/dataset_list.py
qt_dataviewer/dataset_files/dataset_store.py
qt_dataviewer/dataset_files/directory_scanner.py
qt_dataviewer/dataset_files/directory_tree_view.py
qt_dataviewer/dataset_files/generic_xarray.py
qt_dataviewer/dataset_files/qcodes_files.py
qt_dataviewer/model/__init__.py
qt_dataviewer/model/fft.py
qt_dataviewer/model/histograms.py
qt_dataviewer/model/plot_model.py
qt_dataviewer/plot_ui/__init__.py
qt_dataviewer/plot_ui/axis_helper.py
qt_dataviewer/plot_ui/dataarray_plotter.py
qt_dataviewer/plot_ui/info_widget.py
qt_dataviewer/plot_ui/plot_1d.py
qt_dataviewer/plot_ui/plot_2d.py
qt_dataviewer/plot_ui/plot_multiline.py
qt_dataviewer/plot_ui/plot_settings_panel.py
qt_dataviewer/plot_ui/plot_window.py
qt_dataviewer/plot_ui/plots.py
qt_dataviewer/plot_ui/pulses_widget.py
qt_dataviewer/plot_ui/smart_format.py
qt_dataviewer/quantify/__init__.py
qt_dataviewer/quantify/data_browser.py
qt_dataviewer/quantify/dataset.py
qt_dataviewer/quantify/dataset_description.py
qt_dataviewer/quantify/dataset_store.py
qt_dataviewer/resources/Hidden.png
qt_dataviewer-0.4.19.dist-info/licenses/LICENSE
qt_dataviewer-0.4.19.dist-info/METADATA
qt_dataviewer-0.4.19.dist-info/WHEEL
qt_dataviewer-0.4.19.dist-info/top_level.txt
qt_dataviewer-0.4.19.dist-info/RECORD
