Metadata-Version: 2.4
Name: qt_dataviewer
Version: 0.4.19
Summary: QuTech Viewer for xarray Datasets. Supports Core-tools, Quantify and QCoDeS datasets.
Author-email: Sander de Snoo <s.l.desnoo@tudelft.nl>
License-Expression: MIT
Project-URL: Documentation, https://gitlab.tudelft.nl/qutech-qdlabs/qt-dataviewer/-/blob/main/README.md
Project-URL: Repository, https://gitlab.tudelft.nl/qutech-qdlabs/qt-dataviewer
Project-URL: Changelog, https://gitlab.tudelft.nl/qutech-qdlabs/qt-dataviewer/-/blob/main/CHANGELOG.md
Classifier: Programming Language :: Python :: 3
Classifier: Operating System :: OS Independent
Requires-Python: >=3.10
License-File: LICENSE
Requires-Dist: pyqt5>=5.15
Requires-Dist: pyqtgraph>=0.13.7
Requires-Dist: matplotlib>=3.5.3
Requires-Dist: numpy>=1.24
Requires-Dist: xarray
Requires-Dist: h5netcdf
Dynamic: license-file
